{
    "folder": "pointclouds",
    "filename": "Squat_127.ply",
    "path": "pointclouds\\Squat_127.ply",
    "objects": [
        {
            "name": "Squat",
            "centroid": {
                "x": 1.98795227,
                "y": -0.56478656,
                "z": -0.38812837
            },
            "dimensions": {
                "length": 0.75,
                "width": 0.55,
                "height": 0.81
            },
            "rotations": {
                "x": 0,
                "y": 0,
                "z": 0
            }
        }
    ]
}