{
    "folder": "pointclouds",
    "filename": "Squat_27.ply",
    "path": "pointclouds\\Squat_27.ply",
    "objects": [
        {
            "name": "Squat",
            "centroid": {
                "x": 2.35658532,
                "y": -0.69964968,
                "z": -0.44844375
            },
            "dimensions": {
                "length": 0.75,
                "width": 0.55,
                "height": 0.87
            },
            "rotations": {
                "x": 0,
                "y": 0,
                "z": 91
            }
        }
    ]
}